Metadata-Version: 2.1
Name: odoo10-addon-l10n-us-check-writing-address
Version: 10.0.1.1.0.99.dev1
Summary: Print US Checks
Home-page: https://www.opensourceintegrators.com
Author: Open Source Integrators, Odoo Community Association (OCA)
Author-email: support@odoo-community.org
License: AGPL-3
Platform: UNKNOWN
Classifier: Programming Language :: Python
Classifier: Framework :: Odoo
Classifier: License :: OSI Approved :: GNU Affero General Public License v3
Requires-Python: ~=2.7
Requires-Dist: odoo10-addon-account-check-printing-report-base
Requires-Dist: odoo (<10.1dev,>=10.0)
